kivymd/__init__.py
kivymd/_version.py
kivymd/animation.py
kivymd/app.py
kivymd/dynamic_color.py
kivymd/factory_registers.py
kivymd/font_definitions.py
kivymd/icon_definitions.py
kivymd/material_resources.py
kivymd/theming.py
kivymd/effects/__init__.py
kivymd/effects/stiffscroll/__init__.py
kivymd/effects/stiffscroll/stiffscroll.py
kivymd/fonts/Roboto-Black.ttf
kivymd/fonts/Roboto-BlackItalic.ttf
kivymd/fonts/Roboto-Bold.ttf
kivymd/fonts/Roboto-BoldItalic.ttf
kivymd/fonts/Roboto-Italic.ttf
kivymd/fonts/Roboto-Light.ttf
kivymd/fonts/Roboto-LightItalic.ttf
kivymd/fonts/Roboto-Medium.ttf
kivymd/fonts/Roboto-MediumItalic.ttf
kivymd/fonts/Roboto-Regular.ttf
kivymd/fonts/Roboto-Thin.ttf
kivymd/fonts/Roboto-ThinItalic.ttf
kivymd/fonts/materialdesignicons-webfont.ttf
kivymd/images/folder.png
kivymd/images/transparent.png
kivymd/images/logo/kivymd-icon-128.png
kivymd/images/logo/kivymd-icon-256.png
kivymd/images/logo/kivymd-icon-512.png
kivymd/toast/__init__.py
kivymd/toast/androidtoast.py
kivymd/tools/__init__.py
kivymd/tools/argument_parser.py
kivymd/tools/hotreload/__init__.py
kivymd/tools/hotreload/app.py
kivymd/tools/packaging/__init__.py
kivymd/tools/packaging/pyinstaller/__init__.py
kivymd/tools/packaging/pyinstaller/hook-kivymd.py
kivymd/tools/patterns/__init__.py
kivymd/tools/patterns/add_view.py
kivymd/tools/patterns/create_project.py
kivymd/tools/patterns/MVC/__init__.py
kivymd/tools/patterns/MVC/messages.pot
kivymd/tools/patterns/MVC/Model/__init__.py
kivymd/tools/patterns/MVC/Model/database_firebase.py
kivymd/tools/patterns/MVC/Model/database_restdb.py
kivymd/tools/patterns/MVC/data/locales/po/en.po
kivymd/tools/patterns/MVC/data/locales/po/ru.po
kivymd/tools/patterns/MVC/libs/__init__.py
kivymd/tools/patterns/MVC/libs/translation.py
kivymd/uix/__init__.py
kivymd/uix/anchorlayout.py
kivymd/uix/boxlayout.py
kivymd/uix/circularlayout.py
kivymd/uix/floatlayout.py
kivymd/uix/gridlayout.py
kivymd/uix/hero.py
kivymd/uix/recyclegridlayout.py
kivymd/uix/recycleview.py
kivymd2-2.0.1.dist-info/LICENSE
kivymd2-2.0.1.dist-info/METADATA
kivymd2-2.0.1.dist-info/WHEEL
kivymd2-2.0.1.dist-info/entry_points.txt
kivymd2-2.0.1.dist-info/top_level.txt
kivymd2-2.0.1.dist-info/RECORD
