Metadata-Version: 2.1
Name: kivymd2
Version: 2.0.1
Summary: Set of widgets for Kivy inspired by Google's Material Design
Home-page: https://github.com/kivymd/KivyMD
Author: Andres Rodriguez, fork author - Ivanov Yuri, package fork - Jiri Otoupal
Author-email: kivydevelopment@gmail.com
License: MIT
Project-URL: Documentation, https://kivymd.readthedocs.io
Project-URL: Wiki, https://github.com/kivymd/KivyMD/wiki
Project-URL: Tracker, https://github.com/kivymd/KivyMD/issues
Keywords: kivymd,kivy,material,ui
Platform: any
Classifier: Development Status :: 4 - Beta
Classifier: License :: OSI Approved :: MIT License
Classifier: Programming Language :: Python :: 3 :: Only
Classifier: Programming Language :: Python :: 3
Classifier: Programming Language :: Python :: 3.7
Classifier: Programming Language :: Python :: 3.8
Classifier: Programming Language :: Python :: 3.9
Classifier: Programming Language :: Python :: 3.10
Classifier: Operating System :: OS Independent
Classifier: Operating System :: Android
Classifier: Operating System :: POSIX :: Linux
Classifier: Operating System :: POSIX :: BSD :: FreeBSD
Classifier: Operating System :: Microsoft :: Windows
Classifier: Operating System :: iOS
Classifier: Operating System :: MacOS
Classifier: Operating System :: MacOS :: MacOS X
Classifier: Environment :: MacOS X
Classifier: Environment :: Win32 (MS Windows)
Classifier: Environment :: X11 Applications
Classifier: Intended Audience :: Developers
Classifier: Intended Audience :: End Users/Desktop
Classifier: Intended Audience :: Information Technology
Classifier: Intended Audience :: Science/Research
Classifier: Topic :: Software Development :: User Interfaces
Classifier: Topic :: Scientific/Engineering :: Human Machine Interfaces
Classifier: Topic :: Scientific/Engineering :: Visualization
Requires-Python: >=3.7
License-File: LICENSE
Requires-Dist: kivy >=2.3.0
Requires-Dist: pillow
Requires-Dist: materialyoucolor >=2.0.7
Requires-Dist: exceptiongroup
Requires-Dist: asyncgui
Requires-Dist: asynckivy <0.7,>=0.6
Provides-Extra: dev
Requires-Dist: pre-commit ; extra == 'dev'
Requires-Dist: black ; extra == 'dev'
Requires-Dist: isort[pyproject] ; extra == 'dev'
Requires-Dist: flake8 ; extra == 'dev'
Requires-Dist: pytest ; extra == 'dev'
Requires-Dist: pytest-cov ; extra == 'dev'
Requires-Dist: pytest-asyncio ; extra == 'dev'
Requires-Dist: pytest-timeout ; extra == 'dev'
Requires-Dist: coveralls ; extra == 'dev'
Requires-Dist: pyinstaller[hook_testing] ; extra == 'dev'
Provides-Extra: docs
Requires-Dist: sphinx ==7.3.7 ; extra == 'docs'
Requires-Dist: sphinx-autoapi ==3.0.0 ; extra == 'docs'
Requires-Dist: sphinx-book-theme ; extra == 'docs'
Requires-Dist: sphinx-notfound-page ; extra == 'docs'
Requires-Dist: sphinx-copybutton ; extra == 'docs'
Requires-Dist: sphinx-tabs ; extra == 'docs'
